Metadata-Version: 2.1
Name: selenium-bolid
Version: 1.4
Summary: SeleniumMtehods
Home-page: UNKNOWN
Author-email: gorelov2895@yandex.ru
License: UNKNOWN
Platform: UNKNOWN
